tplbuild/__init__.py
tplbuild/__main__.py
tplbuild/_version.py
tplbuild/arch.py
tplbuild/builtin_clients.yml
tplbuild/config.py
tplbuild/context.py
tplbuild/exceptions.py
tplbuild/executor.py
tplbuild/exit_context.py
tplbuild/graph.py
tplbuild/hashing.py
tplbuild/images.py
tplbuild/jinja_source_mapper.py
tplbuild/output.py
tplbuild/plan.py
tplbuild/py.typed
tplbuild/render.py
tplbuild/sync_to_async_pipe.py
tplbuild/tplbuild.py
tplbuild/utils.py
tplbuild/cmd/__init__.py
tplbuild/cmd/base_build.py
tplbuild/cmd/base_lookup.py
tplbuild/cmd/base_prune.py
tplbuild/cmd/build.py
tplbuild/cmd/common.py
tplbuild/cmd/main.py
tplbuild/cmd/publish.py
tplbuild/cmd/source_lookup.py
tplbuild/cmd/source_update.py
tplbuild/cmd/utility.py
tplbuild/cmd/version.py
tplbuild-0.1.3.dist-info/LICENSE
tplbuild-0.1.3.dist-info/METADATA
tplbuild-0.1.3.dist-info/WHEEL
tplbuild-0.1.3.dist-info/entry_points.txt
tplbuild-0.1.3.dist-info/top_level.txt
tplbuild-0.1.3.dist-info/RECORD
