Metadata-Version: 2.1
Name: tplbuild
Version: 0.1.3
Summary: Templated container build tool
Home-page: http://github.com/msg555/tplbuild/
Author: Mark Gordon
Author-email: msg555@gmail.com
Classifier: Programming Language :: Python
Classifier: Programming Language :: Python :: 3
Classifier: Programming Language :: Python :: 3.8
Classifier: Programming Language :: Python :: 3.9
Classifier: Programming Language :: Python :: 3.10
Classifier: License :: OSI Approved :: BSD License
Classifier: Operating System :: OS Independent
Requires-Python: >=3.8
License-File: LICENSE
Requires-Dist: jinja2 ~=3.0
Requires-Dist: pydantic <3,>=1
Requires-Dist: pyyaml <7,>=5
Requires-Dist: aioregistry ~=0.7.2
